pylinky/__init__.py
pylinky/__main__.py
pylinky/abstractauth.py
pylinky/client.py
pylinky/exceptions.py
pylinky/linkyapi.py
tests/__init__.py
tests/test_client.py
pylinky-0.5.0.dist-info/LICENSE
pylinky-0.5.0.dist-info/METADATA
pylinky-0.5.0.dist-info/WHEEL
pylinky-0.5.0.dist-info/entry_points.txt
pylinky-0.5.0.dist-info/top_level.txt
pylinky-0.5.0.dist-info/RECORD
