Metadata-Version: 2.1
Name: pylinky
Version: 0.5.0
Summary: Get your consumption data from your Enedis account (www.enedis.fr)
Home-page: https://github.com/Pirionfr/pyLinky
Author: Dimitri Capitaine
Author-email: grytes29@gmail.com
License: Apache 2.0
Platform: UNKNOWN
Classifier: Programming Language :: Python :: 3.5
Classifier: Programming Language :: Python :: 3.6
Classifier: Programming Language :: Python :: 3.7
Requires-Dist: python-dateutil
Requires-Dist: requests
Requires-Dist: simplejson
Requires-Dist: requests-oauthlib
Requires-Dist: oauthlib
